odoo/addons/mandate_partner_bank_creation/__init__.py
odoo/addons/mandate_partner_bank_creation/__manifest__.py
odoo/addons/mandate_partner_bank_creation/listeners/__init__.py
odoo/addons/mandate_partner_bank_creation/listeners/partner_bank_listener.py
odoo14_addon_mandate_partner_bank_creation-14.0.0.0.1.dist-info/METADATA
odoo14_addon_mandate_partner_bank_creation-14.0.0.0.1.dist-info/WHEEL
odoo14_addon_mandate_partner_bank_creation-14.0.0.0.1.dist-info/top_level.txt
odoo14_addon_mandate_partner_bank_creation-14.0.0.0.1.dist-info/RECORD
