Metadata-Version: 2.1
Name: odoo14-addon-mandate-partner-bank-creation
Version: 14.0.0.0.1
Summary: When a Res Partner Bank is created, a Account Banking Mandate is created too
Home-page: https://coopdevs.org
Author: Coopdevs Treball SCCL
License: AGPL-3
Platform: UNKNOWN
Classifier: Programming Language :: Python
Classifier: Framework :: Odoo
Classifier: License :: OSI Approved :: GNU Affero General Public License v3
Requires-Python: >=3.6
Requires-Dist: odoo14-addon-account-banking-mandate
Requires-Dist: odoo14-addon-component-event
Requires-Dist: odoo (<14.1dev,>=14.0a)
